fractals.py
main.py
fractalizer_haongo138-0.0.1.dist-info/LICENSE
fractalizer_haongo138-0.0.1.dist-info/METADATA
fractalizer_haongo138-0.0.1.dist-info/WHEEL
fractalizer_haongo138-0.0.1.dist-info/top_level.txt
fractalizer_haongo138-0.0.1.dist-info/RECORD
