Metadata-Version: 2.1
Name: fractalizer_haongo138
Version: 0.0.1
Summary: Generate and display various fractals
Author-email: Hao Ngo <haoxray@gmail.com>
Project-URL: Homepage, https://github.com/haongo138/oss-fractalizer
Classifier: Programming Language :: Python :: 3
Classifier: License :: OSI Approved :: MIT License
Classifier: Operating System :: OS Independent
Requires-Python: >=3.8
License-File: LICENSE
